harpiamm/__init__.py
harpiamm/cam_focus_test.py
harpiamm/delay_line_alignment.py
harpiamm/dod_sens.py
harpiamm/harpiamm.py
harpiamm/harpiamm_ui.py
harpiamm/harpiamm_ui_cli.py
harpiamm/harpiamm_ui_qt.py
harpiamm/list_flir_cameras.py
harpiamm/overlap_analysis.py
harpiamm/read_harpia_config_test.py
scripts/dep_check.py
scripts/run_analyze_beam_overlap.py
scripts/run_cam_focus_scan.py
scripts/run_delay_line_scan.py
harpiamm-2.2.0.dist-info/METADATA
harpiamm-2.2.0.dist-info/SOURCES-Sirius.txt
harpiamm-2.2.0.dist-info/WHEEL
harpiamm-2.2.0.dist-info/top_level.txt
harpiamm-2.2.0.dist-info/RECORD
