Metadata-Version: 2.4
Name: harpiamm
Version: 2.2.0
Summary: A Python library for the HARPIA microscopy module.
Author-email: Lukas Kontenis <lukas.kontenis@lightcon.com>
Requires-Python: >=3.8
Requires-Dist: numpy<2,>=1.24
Requires-Dist: lightcon>=1.5.5
Requires-Dist: spinnaker-python>=4.0.0.0
Requires-Dist: lkcom>=0.5.0
Requires-Dist: lkfit>=0.3.1
Requires-Dist: scikit-image
